paw/__init__.py
paw/config.py
paw/main.py
paw/utils.py
paw/commands/__init__.py
paw/commands/add.py
paw/commands/build.py
paw/commands/check.py
paw/commands/cite.py
paw/commands/csl.py
paw/commands/easter_eggs.py
paw/commands/new.py
paw/commands/shake.py
paw/commands/template.py
paw/commands/zotero.py
paw/templates/__init__.py
paw/templates/file_templates.py
paw_cli-0.6.0.dist-info/METADATA
paw_cli-0.6.0.dist-info/WHEEL
paw_cli-0.6.0.dist-info/entry_points.txt
paw_cli-0.6.0.dist-info/top_level.txt
paw_cli-0.6.0.dist-info/RECORD
