Metadata-Version: 2.4
Name: paw-cli
Version: 0.6.0
Summary: Pandoc Academic Workflow (PAW) CLI tool
Author-email: KawaroX <wkawaro@gmail.com>
License-Expression: MIT
Classifier: Programming Language :: Python :: 3
Classifier: Operating System :: OS Independent
Requires-Python: >=3.8
Requires-Dist: typer
Requires-Dist: rich
Requires-Dist: ruamel-yaml>=0.18.14
Requires-Dist: pybtex>=0.24.0
Requires-Dist: pyperclip>=1.9.0
Requires-Dist: requests>=2.32.4
